{
    "sftpUserDetails": {
        "sftpFile_CACommaSymbol": {
            "sftpFileLocation": "sftp-qa-user:/uploads/cost_accounts/automation_costAccount/importBasicParentCA.csv",
            "sftpServerURL": "sftp-qa.sendpro360.pitneycloud.com:22",
            "sftpUserName": "sftp-qa-user",
            "sftpPassword": "@DVXZNdpAgNM",
            "emailIdForNotification": "hamsa.nachimuthu@pb.com"
        },
        "sftpFile_CAComma_Enterprise": {
            "sftpFileLocation": "sftp-qa-user:/uploads/cost_accounts/automation_costAccount/Auto Import Cost Account_Enterprise_Comma.csv",
            "sftpServerURL": "sftp-qa.sendpro360.pitneycloud.com:22",
            "sftpUserName": "sftp-qa-user",
            "sftpPassword": "@DVXZNdpAgNM",
            "emailIdForNotification": "hamsa.nachimuthu@pb.com"
        },
        "sftpFile_CAComma_Division": {
            "sftpFileLocation": "sftp-qa-user:/uploads/cost_accounts/automation_costAccount/Auto Import Cost Account_Division_Comma.csv",
            "sftpServerURL": "sftp-qa.sendpro360.pitneycloud.com:22",
            "sftpUserName": "sftp-qa-user",
            "sftpPassword": "@DVXZNdpAgNM",
            "emailIdForNotification": "hamsa.nachimuthu@pb.com"
        },
        "sftpFile_CAComma_Location": {
            "sftpFileLocation": "sftp-qa-user:/uploads/cost_accounts/automation_costAccount/Auto Import Cost Account_Location_Comma.csv",
            "sftpServerURL": "sftp-qa.sendpro360.pitneycloud.com:22",
            "sftpUserName": "sftp-qa-user",
            "sftpPassword": "@DVXZNdpAgNM",
            "emailIdForNotification": "hamsa.nachimuthu@pb.com"
        },
        "sftpFile_CAComma_MultiLocation": {
            "sftpFileLocation": "sftp-qa-user:/uploads/cost_accounts/automation_costAccount/Auto Import Cost Account_MultiLocation_Comma.csv",
            "sftpServerURL": "sftp-qa.sendpro360.pitneycloud.com:22",
            "sftpUserName": "sftp-qa-user",
            "sftpPassword": "@DVXZNdpAgNM",
            "emailIdForNotification": "hamsa.nachimuthu@pb.com"
        },
        "sftpFile_CAComma_Active": {
            "sftpFileLocation": "sftp-qa-user:/uploads/cost_accounts/automation_costAccount/Auto Import Cost Account_Active.csv",
            "sftpServerURL": "sftp-qa.sendpro360.pitneycloud.com:22",
            "sftpUserName": "sftp-qa-user",
            "sftpPassword": "@DVXZNdpAgNM",
            "emailIdForNotification": "hamsa.nachimuthu@pb.com"
        },
        "sftpFile_CAComma_Inactive": {
            "sftpFileLocation": "sftp-qa-user:/uploads/cost_accounts/automation_costAccount/Auto Import Cost Account_ActiveToInactive.csv",
            "sftpServerURL": "sftp-qa.sendpro360.pitneycloud.com:22",
            "sftpUserName": "sftp-qa-user",
            "sftpPassword": "@DVXZNdpAgNM",
            "emailIdForNotification": "hamsa.nachimuthu@pb.com"
        },
        "sftpFile_CAComma_LocToEnterprise": {
            "sftpFileLocation": "sftp-qa-user:/uploads/cost_accounts/automation_costAccount/Auto Import Cost Account_LocationToEnterprise.csv",
            "sftpServerURL": "sftp-qa.sendpro360.pitneycloud.com:22",
            "sftpUserName": "sftp-qa-user",
            "sftpPassword": "@DVXZNdpAgNM",
            "emailIdForNotification": "hamsa.nachimuthu@pb.com"
        },
        "sftpFile_CAComma_Loc_SamecodeDiffname": {
            "sftpFileLocation": "sftp-qa-user:/uploads/cost_accounts/automation_costAccount/Auto Import Cost Account_Loc_SamecodeDiffname.csv",
            "sftpServerURL": "sftp-qa.sendpro360.pitneycloud.com:22",
            "sftpUserName": "sftp-qa-user",
            "sftpPassword": "@DVXZNdpAgNM",
            "emailIdForNotification": "hamsa.nachimuthu@pb.com"
        },
        "sftpFile_CAComma_Loc_SamenameDiffcode": {
            "sftpFileLocation": "sftp-qa-user:/uploads/cost_accounts/automation_costAccount/Auto Import Cost Account_Division_SamenameDiffcode.csv",
            "sftpServerURL": "sftp-qa.sendpro360.pitneycloud.com:22",
            "sftpUserName": "sftp-qa-user",
            "sftpPassword": "@DVXZNdpAgNM",
            "emailIdForNotification": "hamsa.nachimuthu@pb.com"
        },
        "sftpFile_CAComma_MultiLocation_Loc1ToLoc2": {
            "sftpFileLocation": "sftp-qa-user:/uploads/cost_accounts/automation_costAccount/Auto Import Cost Account_MultiLocation_Comma_Loc1toLoc2.csv",
            "sftpServerURL": "sftp-qa.sendpro360.pitneycloud.com:22",
            "sftpUserName": "sftp-qa-user",
            "sftpPassword": "@DVXZNdpAgNM",
            "emailIdForNotification": "hamsa.nachimuthu@pb.com"
        }
    }
}